[
  {
    "question": "In the lesson, what was the 'smart' way discussed to calculate 71 x 999?",
    "correct": "71 * (1000 - 1)",
    "options": [
      "71 * (1000 - 1)",
      "71 * 900 + 71 * 99",
      "Multiplying it directly column by column",
      "Using a calculator"
    ],
    "difficulty": "medium",
    "questionType": "mcq",
    "topic": "Mathematics - Distributive Property",
    "complexity_score": 2
  },
  {
    "question": "Based on the lesson, what is the sum of the first 12 odd numbers?",
    "correct": "144",
    "options": [
      "12",
      "24",
      "144",
      "120"
    ],
    "difficulty": "easy",
    "questionType": "mcq",
    "topic": "Mathematics - Number Patterns",
    "complexity_score": 1
  },
  {
    "question": "According to the science chapter discussed, what is the definition of an 'object'?",
    "correct": "Anything that can be seen or touched",
    "options": [
      "Only things made of wood",
      "Anything that can be seen or touched",
      "The matter used to make things",
      "Only non-living things"
    ],
    "difficulty": "easy",
    "questionType": "mcq",
    "topic": "Science - Kinds of Material",
    "complexity_score": 1
  },
  {
    "question": "What is the definition of a 'material' as explained in the science text?",
    "correct": "The matter of which an object is made",
    "options": [
      "A type of book",
      "The final product, like a chair",
      "Anything that has a shape",
      "The matter of which an object is made"
    ],
    "difficulty": "easy",
    "questionType": "mcq",
    "topic": "Science - Kinds of Material",
    "complexity_score": 1
  },
  {
    "question": "Using the pattern n², what is the sum of the first 50 odd numbers?",
    "correct": "2500",
    "options": [
      "50",
      "100",
      "2500",
      "500"
    ],
    "difficulty": "medium",
    "questionType": "mcq",
    "topic": "Mathematics - Number Patterns",
    "complexity_score": 2
  },
  {
    "question": "Which of the following is an example of a material discussed in the class?",
    "correct": "Plastic",
    "options": [
      "Pencil Box",
      "Plastic",
      "Coin",
      "Ball"
    ],
    "difficulty": "easy",
    "questionType": "mcq",
    "topic": "Science - Kinds of Material",
    "complexity_score": 1
  },
  {
    "question": "Which of the following is an example of an object?",
    "correct": "A chair",
    "options": [
      "Wood",
      "Metal",
      "A chair",
      "Glass"
    ],
    "difficulty": "easy",
    "questionType": "mcq",
    "topic": "Science - Kinds of Material",
    "complexity_score": 1
  },
  {
    "question": "In the math challenge, how did the tutor suggest breaking down the number 9 to solve 18.9 * 9 efficiently?",
    "correct": "10 - 1",
    "options": [
      "3 * 3",
      "5 + 4",
      "10 - 1",
      "9 * 1"
    ],
    "difficulty": "medium",
    "questionType": "mcq",
    "topic": "Mathematics - Distributive Property",
    "complexity_score": 2
  },
  {
    "question": "What number, when multiplied by 8, gives 1000?",
    "correct": "125",
    "options": [
      "100",
      "125",
      "250",
      "500"
    ],
    "difficulty": "easy",
    "questionType": "mcq",
    "topic": "Mathematics - Arithmetic",
    "complexity_score": 1
  },
  {
    "question": "A chair is an object. What is the material it is made of, according to the example?",
    "correct": "Wood",
    "options": [
      "Soil",
      "Rubber",
      "Wood",
      "Fiber"
    ],
    "difficulty": "easy",
    "questionType": "mcq",
    "topic": "Science - Kinds of Material",
    "complexity_score": 1
  },
  {
    "question": "What is the final answer for 71 * 999, using the method discussed?",
    "correct": "70929",
    "options": [
      "71000",
      "70929",
      "71071",
      "7029"
    ],
    "difficulty": "medium",
    "questionType": "mcq",
    "topic": "Mathematics - Arithmetic",
    "complexity_score": 3
  },
  {
    "question": "The tutor shared a quote about spending time sharpening an axe before cutting a tree. What does this mean in problem-solving?",
    "correct": "Spend time understanding the question first",
    "options": [
      "Work as fast as possible",
      "Always use the sharpest pencil",
      "Spend time understanding the question first",
      "Give up if the problem is too hard"
    ],
    "difficulty": "hard",
    "questionType": "mcq",
    "topic": "Problem-Solving Strategy",
    "complexity_score": 4
  },
  {
    "question": "Complete the sentence from the science text: All objects are made of different _______.",
    "correct": "materials",
    "options": [
      "shapes",
      "sizes",
      "colors",
      "materials"
    ],
    "difficulty": "easy",
    "questionType": "mcq",
    "topic": "Science - Kinds of Material",
    "complexity_score": 1
  },
  {
    "question": "What is the sum of the first 15 odd numbers?",
    "correct": "225",
    "options": [
      "150",
      "30",
      "225",
      "215"
    ],
    "difficulty": "medium",
    "questionType": "mcq",
    "topic": "Mathematics - Number Patterns",
    "complexity_score": 2
  },
  {
    "question": "Which of these was NOT listed as an example of a material in the lesson?",
    "correct": "Mud",
    "options": [
      "Leather",
      "Plastic",
      "Wood",
      "Mud"
    ],
    "difficulty": "medium",
    "questionType": "mcq",
    "topic": "Science - Kinds of Material",
    "complexity_score": 2
  },
  {
    "question": "How many questions did Kavya need to solve in the 15-minute challenge to earn 100 XP?",
    "correct": "At least 5",
    "options": [
      "15",
      "10",
      "At least 5",
      "Exactly 1"
    ],
    "difficulty": "easy",
    "questionType": "mcq",
    "topic": "Class Activity",
    "complexity_score": 1
  },
  {
    "question": "What is the result of 12 x 12?",
    "correct": "144",
    "options": [
      "24",
      "124",
      "144",
      "1212"
    ],
    "difficulty": "easy",
    "questionType": "mcq",
    "topic": "Mathematics - Arithmetic",
    "complexity_score": 1
  },
  {
    "question": "In the equation `(___ / 8) * 168 = 125 * 168`, what number goes in the blank to make it true?",
    "correct": "1000",
    "options": [
      "125",
      "168",
      "8",
      "1000"
    ],
    "difficulty": "medium",
    "questionType": "mcq",
    "topic": "Mathematics - Algebra",
    "complexity_score": 3
  },
  {
    "question": "What is the relationship between an object and a material?",
    "correct": "An object is made of one or more materials",
    "options": [
      "They are the same thing",
      "A material is made of objects",
      "An object is made of one or more materials",
      "They have no relationship"
    ],
    "difficulty": "medium",
    "questionType": "mcq",
    "topic": "Science - Kinds of Material",
    "complexity_score": 2
  },
  {
    "question": "Which two subjects were primarily focused on during the session?",
    "correct": "Maths and Science",
    "options": [
      "English and Social Science",
      "Maths and Science",
      "Science and English",
      "Maths and Social Science"
    ],
    "difficulty": "easy",
    "questionType": "mcq",
    "topic": "General Knowledge",
    "complexity_score": 1
  }
]